rda_python_common/PgCMD.py
rda_python_common/PgDBI.py
rda_python_common/PgFile.py
rda_python_common/PgLOG.py
rda_python_common/PgLock.py
rda_python_common/PgOPT.py
rda_python_common/PgSIG.py
rda_python_common/PgSplit.py
rda_python_common/PgUtil.py
rda_python_common/__init__.py
rda_python_common/pg_cmd.py
rda_python_common/pg_dbi.py
rda_python_common/pg_file.py
rda_python_common/pg_lock.py
rda_python_common/pg_log.py
rda_python_common/pg_opt.py
rda_python_common/pg_password.py
rda_python_common/pg_sig.py
rda_python_common/pg_split.py
rda_python_common/pg_util.py
rda_python_common/pgpassword.py
rda_python_common-2.0.16.dist-info/licenses/LICENSE
rda_python_common-2.0.16.dist-info/METADATA
rda_python_common-2.0.16.dist-info/WHEEL
rda_python_common-2.0.16.dist-info/entry_points.txt
rda_python_common-2.0.16.dist-info/top_level.txt
rda_python_common-2.0.16.dist-info/RECORD
