Metadata-Version: 2.4
Name: rda_python_common
Version: 2.0.16
Summary: RDA Python common library codes shared by other RDA python packages
Author-email: Zaihua Ji <zji@ucar.edu>
Project-URL: Homepage, https://github.com/NCAR/rda-python-common
Classifier: Programming Language :: Python :: 3
Classifier: License :: OSI Approved :: MIT License
Classifier: Operating System :: OS Independent
Classifier: Development Status :: 5 - Production/Stable
Requires-Python: >=3.7
License-File: LICENSE
Requires-Dist: psycopg2-binary
Requires-Dist: rda-python-globus
Requires-Dist: unidecode
Dynamic: license-file
